ddos_avoider/__init__.py
ddos_avoider-0.0.1.dist-info/METADATA
ddos_avoider-0.0.1.dist-info/WHEEL
ddos_avoider-0.0.1.dist-info/top_level.txt
ddos_avoider-0.0.1.dist-info/RECORD
